README.rst
setup.cfg
setup.py
./__init__.py
./incoterm.py
./invoice.py
./invoice.xml
./sale.py
./sale.xml
./stock.py
./stock.xml
./tryton.cfg
./tests/__init__.py
./tests/test_incoterm.py
./tests/test_sale.py
./view/invoice_form.xml
./view/invoice_incoterm_form.xml
./view/invoice_incoterm_tree.xml
./view/sale_form.xml
./view/sale_incoterm_form.xml
./view/sale_incoterm_tree.xml
./view/stock_form.xml
./view/stock_incoterm_form.xml
./view/stock_incoterm_tree.xml
openlabs_incoterm.egg-info/PKG-INFO
openlabs_incoterm.egg-info/SOURCES.txt
openlabs_incoterm.egg-info/dependency_links.txt
openlabs_incoterm.egg-info/entry_points.txt
openlabs_incoterm.egg-info/not-zip-safe
openlabs_incoterm.egg-info/requires.txt
openlabs_incoterm.egg-info/top_level.txt